odoo10_addon_shopinvader_algolia-10.0.1.0.0.99.dev24-py3.8-nspkg.pth
odoo/addons/shopinvader_algolia/README.rst
odoo/addons/shopinvader_algolia/__init__.py
odoo/addons/shopinvader_algolia/__manifest__.py
odoo/addons/shopinvader_algolia/hooks.py
odoo/addons/shopinvader_algolia/components/__init__.py
odoo/addons/shopinvader_algolia/components/deleter.py
odoo/addons/shopinvader_algolia/components/exporter.py
odoo/addons/shopinvader_algolia/data/ir_export_product.xml
odoo/addons/shopinvader_algolia/demo/backend_demo.xml
odoo/addons/shopinvader_algolia/demo/product_demo.xml
odoo/addons/shopinvader_algolia/i18n/shopinvader_algolia.pot
odoo/addons/shopinvader_algolia/models/__init__.py
odoo/addons/shopinvader_algolia/models/shopinvader_product.py
odoo/addons/shopinvader_algolia/readme/CONTRIBUTORS.rst
odoo/addons/shopinvader_algolia/readme/CREDITS.rst
odoo/addons/shopinvader_algolia/readme/DESCRIPTION.rst
odoo/addons/shopinvader_algolia/static/description/icon.png
odoo/addons/shopinvader_algolia/static/description/index.html
odoo/addons/shopinvader_algolia/tests/__init__.py
odoo/addons/shopinvader_algolia/tests/test_export.py
odoo/addons/shopinvader_algolia/tests/cassettes/TestAlgoliaBackend.test_10_export_one_product.yaml
odoo/addons/shopinvader_algolia/tests/cassettes/TestAlgoliaBackend.test_20_export_all_products.yaml
odoo/addons/shopinvader_algolia/tests/cassettes/TestAlgoliaBackend.test_30_export_all_categories.yaml
odoo10_addon_shopinvader_algolia-10.0.1.0.0.99.dev24.dist-info/METADATA
odoo10_addon_shopinvader_algolia-10.0.1.0.0.99.dev24.dist-info/WHEEL
odoo10_addon_shopinvader_algolia-10.0.1.0.0.99.dev24.dist-info/namespace_packages.txt
odoo10_addon_shopinvader_algolia-10.0.1.0.0.99.dev24.dist-info/top_level.txt
odoo10_addon_shopinvader_algolia-10.0.1.0.0.99.dev24.dist-info/RECORD
